peucr_core/__init__.py
peucr_core/exceptions.py
peucr_core/framework.py
peucr_core/loaders.py
peucr_core/plugin.py
peucr_core/pluginsuite.py
peucr_core/validator.py
peucr_core/validatorsuite.py
peucr_core/plugins/__init__.py
peucr_core/plugins/http.py
peucr_core/plugins/sqs_purge.py
peucr_core/plugins/sqs_receive.py
peucr_core/plugins/sqs_send.py
peucr_core/validators/__init__.py
peucr_core/validators/default.py
peucr_core/validators/json.py
peucr_core/validators/oneof.py
peucr_core/validators/status.py
peucr_core-0.3.0.dist-info/LICENSE
peucr_core-0.3.0.dist-info/METADATA
peucr_core-0.3.0.dist-info/WHEEL
peucr_core-0.3.0.dist-info/top_level.txt
peucr_core-0.3.0.dist-info/RECORD
