Metadata-Version: 2.1
Name: peucr-core
Version: 0.3.0
Summary: Plain extensible unified code requirement
Author-email: Ricardo Rodrigues <rsrodrigues@proton.me>
Project-URL: Homepage, https://github.com/kwakiutlCS/peucr-core
Project-URL: Source, https://github.com/kwakiutlCS/peucr-core
Classifier: Programming Language :: Python :: 3
Classifier: License :: OSI Approved :: MIT License
Classifier: Operating System :: OS Independent
Requires-Python: >=3.8
License-File: LICENSE
